MANIFEST.in
README.rst
setup.py
scell/__init__.py
scell/core.py
scell/wrapper.py
scell.egg-info/PKG-INFO
scell.egg-info/SOURCES.txt
scell.egg-info/dependency_links.txt
scell.egg-info/not-zip-safe
scell.egg-info/pbr.json
scell.egg-info/requires.txt
scell.egg-info/top_level.txt