Metadata-Version: 1.1
Name: scell
Version: 0.3.1
Summary: simple wrapper atop select
Home-page: https://github.com/eugene-eeo/scell
Author: Eugene Eeo
Author-email: packwolf58@gmail.com
License: MIT
Keywords: selector io reactor
Platform: any
Classifier: Development Status :: 4 - Beta
Classifier: Intended Audience :: Developers
Classifier: Operating System :: OS Independent
Classifier: Programming Language :: Python
Classifier: Programming Language :: Python :: 3
Classifier: License :: OSI Approved :: MIT License
